leaf_example/__init__.py
leaf_example/adapter.py
leaf_example/device.json
leaf_example/example.yaml
leaf_example/interpreter.py
leaf_example-0.1.0.dist-info/METADATA
leaf_example-0.1.0.dist-info/WHEEL
leaf_example-0.1.0.dist-info/entry_points.txt
leaf_example-0.1.0.dist-info/licenses/LICENSE
leaf_example-0.1.0.dist-info/RECORD
