Metadata-Version: 2.4
Name: leaf-example
Version: 0.1.0
Summary: Leaf Adapter with a basic example function. Creating a measurement message every x interval.
License-File: LICENSE
Author: Jasper Koehorst
Author-email: jasper.koehorst@wur.nl
Requires-Python: >=3.12,<4.0
Classifier: Programming Language :: Python :: 3
Classifier: Programming Language :: Python :: 3.12
Classifier: Programming Language :: Python :: 3.13
Classifier: Programming Language :: Python :: 3.14
Requires-Dist: leaf-framework
